ppa_copy_packages.py
ppa_copy_packages-1.9.4.dist-info/METADATA
ppa_copy_packages-1.9.4.dist-info/WHEEL
ppa_copy_packages-1.9.4.dist-info/entry_points.txt
ppa_copy_packages-1.9.4.dist-info/top_level.txt
ppa_copy_packages-1.9.4.dist-info/RECORD
