Metadata-Version: 2.1
Name: ppa-copy-packages
Version: 1.9.4
Summary: Copy Ubuntu PPA packages from one release pocket to another
Home-page: https://github.com/mgedmin/ppa-copy-packages
Author: Marius Gedminas
Author-email: marius@gedmin.as
License: GPL
Keywords: ubuntu ppa launchpad copy automation
Platform: UNKNOWN
Classifier: Development Status :: 4 - Beta
Classifier: Environment :: Console
Classifier: Intended Audience :: Developers
Classifier: License :: OSI Approved :: GNU General Public License (GPL)
Classifier: Operating System :: OS Independent
Classifier: Programming Language :: Python
Classifier: Programming Language :: Python :: 2.7
Classifier: Programming Language :: Python :: 3.5
Classifier: Programming Language :: Python :: 3.6
Classifier: Programming Language :: Python :: 3.7
Requires-Python: >=2.7, !=3.0.*, !=3.1.*, !=3.2.*, !=3.3.*, !=3.4.*
Requires-Dist: launchpadlib
